{
    "authHost": "http://10.90.90.22",
    "authEndpoint": "/broadcasting/auth",
    "clients": [
        {
            "appId": "c8443b640decb1e6",
            "key": "3f2ece6d20d8f21bb182b4c6d8504bd3"
        }
    ],
    "database": "redis",
    "databaseConfig": {
        "redis": {},
        "sqlite": {
            "databasePath": "/database/laravel-echo-server.sqlite"
        }
    },
    "devMode": false,
    "host": null,
    "port": "6001",
    "protocol": "http",
    "socketio": {},
    "secureOptions": 67108864,
    "sslCertPath": "",
    "sslKeyPath": "",
    "sslCertChainPath": "",
    "sslPassphrase": "",
    "subscribers": {
        "http": true,
        "redis": true
    },
    "apiOriginAllow": {
        "allowCors": true,
        "allowOrigin": "http://10.90.90.22",
        "allowMethods": "GET, POST",
        "allowHeaders": "Origin, Content-Type, X-Auth-Token, X-Requested-With, Accept, Authorization, X-CSRF-TOKEN, X-Socket-Id"
    }
}
